Workbook

Sheet Instrucciones
A1: Plantilla de homologación de cotizaciones (E4)
A3: 1. Carga en Partidas el itemizado de la solicitud: código, descripción, unidad,
A4: metrado referencial y costo referencial unitario (presupuesto meta).
A5: Sin esto no se puede comparar el precio ofertado con la referencia.
A6: 2. Llena Parametros con el tipo de cambio autorizado (fecha, fuente y aprobado_por).
A7: 3. En Homologacion, una fila por partida y proveedor. Solo la versión final vigente.
A8: 4. Si un dato no aparece en la cotización, déjalo vacío. No lo inventes.
A9: 5. Las equivalencias y el alcance los decide el especialista: la IA solo propone.
A10: 6. Toda propuesta con dudas queda en Estado revisión = Pendiente.
A12: Las columnas grises con fórmula se calculan solas: no las escribas a mano.
A13: Los datos de negocio (plazo, garantía, validez, forma de pago) se registran desde la cotización original.

Sheet Parametros
A1: Parámetro | B1: Valor | C1: Nota
A2: Tipo de cambio USD a PEN | C2: Autorizado por el especialista
A3: Sentido del cambio | B3: USD_PEN | C3: Solo USD_PEN en esta versión
A4: Fecha del tipo de cambio (AAAA-MM-DD)
A5: Fuente del tipo de cambio | C5: Ej.: SUNAT, banco, acuerdo de contrato
A6: Aprobado por | C6: Especialista que lo autoriza
A7: IGV | B7: 0.18 | C7: Tasa vigente

Sheet Partidas
A1: Código de partida | B1: Descripción | C1: Unidad | D1: Metrado referencial | E1: Costo referencial unitario S/ (presupuesto meta) | F1: Presupuesto referencial S/ (calc.)
F2: =IF(OR(D2="",E2=""),"",D2*E2)
F3: =IF(OR(D3="",E3=""),"",D3*E3)
F4: =IF(OR(D4="",E4=""),"",D4*E4)
F5: =IF(OR(D5="",E5=""),"",D5*E5)
F6: =IF(OR(D6="",E6=""),"",D6*E6)
F7: =IF(OR(D7="",E7=""),"",D7*E7)
F8: =IF(OR(D8="",E8=""),"",D8*E8)
F9: =IF(OR(D9="",E9=""),"",D9*E9)
F10: =IF(OR(D10="",E10=""),"",D10*E10)
F11: =IF(OR(D11="",E11=""),"",D11*E11)
F12: =IF(OR(D12="",E12=""),"",D12*E12)
F13: =IF(OR(D13="",E13=""),"",D13*E13)
... F201: =IF(OR(D201="",E201=""),"",D201*E201)

Sheet Homologacion
A1: Código partida | B1: Descripción partida (itemizado) | C1: Proveedor | D1: Versión final (Sí/No) | E1: Moneda original (PEN/USD) | F1: Unidad ofertada | G1: Cantidad ofertada | H1: Precio unitario original | I1: Precio unitario S/ (calc.) | J1: Metrado referencial (calc.) | K1: Costo referencial unitario S/ (calc.) | L1: Parcial S/ ofertado (calc.) | M1: Presupuesto referencial S/ (calc.) | N1: Desviación de precio vs referencia % (calc.) | O1: Diferencia de metrado (calc.) | P1: IGV incluido (Sí/No/Pendiente) | Q1: Alcance coincide (Sí/No/Pendiente) | R1: Equivalencia propuesta | S1: Archivo de evidencia | T1: Página | U1: Estado revisión (Pendiente/Aprobado/Rechazado) | V1: Observación
I2: =IF(H2="","",IF(E2="USD",H2*Parametros!$B$2,H2)) | J2: =IF(A2="","",IFERROR(VLOOKUP(A2,Partidas!$A$2:$E$201,4,FALSE),"")) | K2: =IF(A2="","",IFERROR(VLOOKUP(A2,Partidas!$A$2:$E$201,5,FALSE),"")) | L2: =IF(OR(I2="",G2=""),"",G2*I2) | M2: =IF(OR(J2="",K2=""),"",J2*K2) | N2: =IF(OR(I2="",K2="",K2=0),"",(I2-K2)/K2) | O2: =IF(OR(G2="",J2=""),"",G2-J2)
I3: =IF(H3="","",IF(E3="USD",H3*Parametros!$B$2,H3)) | J3: =IF(A3="","",IFERROR(VLOOKUP(A3,Partidas!$A$2:$E$201,4,FALSE),"")) | K3: =IF(A3="","",IFERROR(VLOOKUP(A3,Partidas!$A$2:$E$201,5,FALSE),"")) | L3: =IF(OR(I3="",G3=""),"",G3*I3) | M3: =IF(OR(J3="",K3=""),"",J3*K3) | N3: =IF(OR(I3="",K3="",K3=0),"",(I3-K3)/K3) | O3: =IF(OR(G3="",J3=""),"",G3-J3)
I4: =IF(H4="","",IF(E4="USD",H4*Parametros!$B$2,H4)) | J4: =IF(A4="","",IFERROR(VLOOKUP(A4,Partidas!$A$2:$E$201,4,FALSE),"")) | K4: =IF(A4="","",IFERROR(VLOOKUP(A4,Partidas!$A$2:$E$201,5,FALSE),"")) | L4: =IF(OR(I4="",G4=""),"",G4*I4) | M4: =IF(OR(J4="",K4=""),"",J4*K4) | N4: =IF(OR(I4="",K4="",K4=0),"",(I4-K4)/K4) | O4: =IF(OR(G4="",J4=""),"",G4-J4)
I5: =IF(H5="","",IF(E5="USD",H5*Parametros!$B$2,H5)) | J5: =IF(A5="","",IFERROR(VLOOKUP(A5,Partidas!$A$2:$E$201,4,FALSE),"")) | K5: =IF(A5="","",IFERROR(VLOOKUP(A5,Partidas!$A$2:$E$201,5,FALSE),"")) | L5: =IF(OR(I5="",G5=""),"",G5*I5) | M5: =IF(OR(J5="",K5=""),"",J5*K5) | N5: =IF(OR(I5="",K5="",K5=0),"",(I5-K5)/K5) | O5: =IF(OR(G5="",J5=""),"",G5-J5)
I6: =IF(H6="","",IF(E6="USD",H6*Parametros!$B$2,H6)) | J6: =IF(A6="","",IFERROR(VLOOKUP(A6,Partidas!$A$2:$E$201,4,FALSE),"")) | K6: =IF(A6="","",IFERROR(VLOOKUP(A6,Partidas!$A$2:$E$201,5,FALSE),"")) | L6: =IF(OR(I6="",G6=""),"",G6*I6) | M6: =IF(OR(J6="",K6=""),"",J6*K6) | N6: =IF(OR(I6="",K6="",K6=0),"",(I6-K6)/K6) | O6: =IF(OR(G6="",J6=""),"",G6-J6)
I7: =IF(H7="","",IF(E7="USD",H7*Parametros!$B$2,H7)) | J7: =IF(A7="","",IFERROR(VLOOKUP(A7,Partidas!$A$2:$E$201,4,FALSE),"")) | K7: =IF(A7="","",IFERROR(VLOOKUP(A7,Partidas!$A$2:$E$201,5,FALSE),"")) | L7: =IF(OR(I7="",G7=""),"",G7*I7) | M7: =IF(OR(J7="",K7=""),"",J7*K7) | N7: =IF(OR(I7="",K7="",K7=0),"",(I7-K7)/K7) | O7: =IF(OR(G7="",J7=""),"",G7-J7)
I8: =IF(H8="","",IF(E8="USD",H8*Parametros!$B$2,H8)) | J8: =IF(A8="","",IFERROR(VLOOKUP(A8,Partidas!$A$2:$E$201,4,FALSE),"")) | K8: =IF(A8="","",IFERROR(VLOOKUP(A8,Partidas!$A$2:$E$201,5,FALSE),"")) | L8: =IF(OR(I8="",G8=""),"",G8*I8) | M8: =IF(OR(J8="",K8=""),"",J8*K8) | N8: =IF(OR(I8="",K8="",K8=0),"",(I8-K8)/K8) | O8: =IF(OR(G8="",J8=""),"",G8-J8)
I9: =IF(H9="","",IF(E9="USD",H9*Parametros!$B$2,H9)) | J9: =IF(A9="","",IFERROR(VLOOKUP(A9,Partidas!$A$2:$E$201,4,FALSE),"")) | K9: =IF(A9="","",IFERROR(VLOOKUP(A9,Partidas!$A$2:$E$201,5,FALSE),"")) | L9: =IF(OR(I9="",G9=""),"",G9*I9) | M9: =IF(OR(J9="",K9=""),"",J9*K9) | N9: =IF(OR(I9="",K9="",K9=0),"",(I9-K9)/K9) | O9: =IF(OR(G9="",J9=""),"",G9-J9)
I10: =IF(H10="","",IF(E10="USD",H10*Parametros!$B$2,H10)) | J10: =IF(A10="","",IFERROR(VLOOKUP(A10,Partidas!$A$2:$E$201,4,FALSE),"")) | K10: =IF(A10="","",IFERROR(VLOOKUP(A10,Partidas!$A$2:$E$201,5,FALSE),"")) | L10: =IF(OR(I10="",G10=""),"",G10*I10) | M10: =IF(OR(J10="",K10=""),"",J10*K10) | N10: =IF(OR(I10="",K10="",K10=0),"",(I10-K10)/K10) | O10: =IF(OR(G10="",J10=""),"",G10-J10)
I11: =IF(H11="","",IF(E11="USD",H11*Parametros!$B$2,H11)) | J11: =IF(A11="","",IFERROR(VLOOKUP(A11,Partidas!$A$2:$E$201,4,FALSE),"")) | K11: =IF(A11="","",IFERROR(VLOOKUP(A11,Partidas!$A$2:$E$201,5,FALSE),"")) | L11: =IF(OR(I11="",G11=""),"",G11*I11) | M11: =IF(OR(J11="",K11=""),"",J11*K11) | N11: =IF(OR(I11="",K11="",K11=0),"",(I11-K11)/K11) | O11: =IF(OR(G11="",J11=""),"",G11-J11)
I12: =IF(H12="","",IF(E12="USD",H12*Parametros!$B$2,H12)) | J12: =IF(A12="","",IFERROR(VLOOKUP(A12,Partidas!$A$2:$E$201,4,FALSE),"")) | K12: =IF(A12="","",IFERROR(VLOOKUP(A12,Partidas!$A$2:$E$201,5,FALSE),"")) | L12: =IF(OR(I12="",G12=""),"",G12*I12) | M12: =IF(OR(J12="",K12=""),"",J12*K12) | N12: =IF(OR(I12="",K12="",K12=0),"",(I12-K12)/K12) | O12: =IF(OR(G12="",J12=""),"",G12-J12)
I13: =IF(H13="","",IF(E13="USD",H13*Parametros!$B$2,H13)) | J13: =IF(A13="","",IFERROR(VLOOKUP(A13,Partidas!$A$2:$E$201,4,FALSE),"")) | K13: =IF(A13="","",IFERROR(VLOOKUP(A13,Partidas!$A$2:$E$201,5,FALSE),"")) | L13: =IF(OR(I13="",G13=""),"",G13*I13) | M13: =IF(OR(J13="",K13=""),"",J13*K13) | N13: =IF(OR(I13="",K13="",K13=0),"",(I13-K13)/K13) | O13: =IF(OR(G13="",J13=""),"",G13-J13)
... I501: =IF(H501="","",IF(E501="USD",H501*Parametros!$B$2,H501)) | J501: =IF(A501="","",IFERROR(VLOOKUP(A501,Partidas!$A$2:$E$201,4,FALSE),"")) | K501: =IF(A501="","",IFERROR(VLOOKUP(A501,Partidas!$A$2:$E$201,5,FALSE),"")) | L501: =IF(OR(I501="",G501=""),"",G501*I501) | M501: =IF(OR(J501="",K501=""),"",J501*K501) | N501: =IF(OR(I501="",K501="",K501=0),"",(I501-K501)/K501) | O501: =IF(OR(G501="",J501=""),"",G501-J501)

Sheet Listas
A1: PEN | B1: Sí | C1: Pendiente
A2: USD | B2: No | C2: Aprobado
B3: Pendiente | C3: Rechazado

Sheet Resumen
A1: Proveedor | B1: Partidas cotizadas | C1: Total ofertado S/ (sin IGV) | D1: Presupuesto referencial S/ | E1: Diferencia vs referencia S/ | F1: Partidas pendientes de revisión | G1: Partidas con alcance dudoso
B2: =IF(A2="","",COUNTIFS(Homologacion!$C$2:$C$501,A2)) | C2: =IF(A2="","",SUMIFS(Homologacion!$L$2:$L$501,Homologacion!$C$2:$C$501,A2)) | D2: =IF(A2="","",SUMIFS(Homologacion!$M$2:$M$501,Homologacion!$C$2:$C$501,A2)) | E2: =IF(A2="","",C2-D2) | F2: =IF(A2="","",COUNTIFS(Homologacion!$C$2:$C$501,A2,Homologacion!$U$2:$U$501,"Pendiente")) | G2: =IF(A2="","",COUNTIFS(Homologacion!$C$2:$C$501,A2,Homologacion!$Q$2:$Q$501,"Pendiente"))
B3: =IF(A3="","",COUNTIFS(Homologacion!$C$2:$C$501,A3)) | C3: =IF(A3="","",SUMIFS(Homologacion!$L$2:$L$501,Homologacion!$C$2:$C$501,A3)) | D3: =IF(A3="","",SUMIFS(Homologacion!$M$2:$M$501,Homologacion!$C$2:$C$501,A3)) | E3: =IF(A3="","",C3-D3) | F3: =IF(A3="","",COUNTIFS(Homologacion!$C$2:$C$501,A3,Homologacion!$U$2:$U$501,"Pendiente")) | G3: =IF(A3="","",COUNTIFS(Homologacion!$C$2:$C$501,A3,Homologacion!$Q$2:$Q$501,"Pendiente"))
B4: =IF(A4="","",COUNTIFS(Homologacion!$C$2:$C$501,A4)) | C4: =IF(A4="","",SUMIFS(Homologacion!$L$2:$L$501,Homologacion!$C$2:$C$501,A4)) | D4: =IF(A4="","",SUMIFS(Homologacion!$M$2:$M$501,Homologacion!$C$2:$C$501,A4)) | E4: =IF(A4="","",C4-D4) | F4: =IF(A4="","",COUNTIFS(Homologacion!$C$2:$C$501,A4,Homologacion!$U$2:$U$501,"Pendiente")) | G4: =IF(A4="","",COUNTIFS(Homologacion!$C$2:$C$501,A4,Homologacion!$Q$2:$Q$501,"Pendiente"))
B5: =IF(A5="","",COUNTIFS(Homologacion!$C$2:$C$501,A5)) | C5: =IF(A5="","",SUMIFS(Homologacion!$L$2:$L$501,Homologacion!$C$2:$C$501,A5)) | D5: =IF(A5="","",SUMIFS(Homologacion!$M$2:$M$501,Homologacion!$C$2:$C$501,A5)) | E5: =IF(A5="","",C5-D5) | F5: =IF(A5="","",COUNTIFS(Homologacion!$C$2:$C$501,A5,Homologacion!$U$2:$U$501,"Pendiente")) | G5: =IF(A5="","",COUNTIFS(Homologacion!$C$2:$C$501,A5,Homologacion!$Q$2:$Q$501,"Pendiente"))
B6: =IF(A6="","",COUNTIFS(Homologacion!$C$2:$C$501,A6)) | C6: =IF(A6="","",SUMIFS(Homologacion!$L$2:$L$501,Homologacion!$C$2:$C$501,A6)) | D6: =IF(A6="","",SUMIFS(Homologacion!$M$2:$M$501,Homologacion!$C$2:$C$501,A6)) | E6: =IF(A6="","",C6-D6) | F6: =IF(A6="","",COUNTIFS(Homologacion!$C$2:$C$501,A6,Homologacion!$U$2:$U$501,"Pendiente")) | G6: =IF(A6="","",COUNTIFS(Homologacion!$C$2:$C$501,A6,Homologacion!$Q$2:$Q$501,"Pendiente"))
B7: =IF(A7="","",COUNTIFS(Homologacion!$C$2:$C$501,A7)) | C7: =IF(A7="","",SUMIFS(Homologacion!$L$2:$L$501,Homologacion!$C$2:$C$501,A7)) | D7: =IF(A7="","",SUMIFS(Homologacion!$M$2:$M$501,Homologacion!$C$2:$C$501,A7)) | E7: =IF(A7="","",C7-D7) | F7: =IF(A7="","",COUNTIFS(Homologacion!$C$2:$C$501,A7,Homologacion!$U$2:$U$501,"Pendiente")) | G7: =IF(A7="","",COUNTIFS(Homologacion!$C$2:$C$501,A7,Homologacion!$Q$2:$Q$501,"Pendiente"))
B8: =IF(A8="","",COUNTIFS(Homologacion!$C$2:$C$501,A8)) | C8: =IF(A8="","",SUMIFS(Homologacion!$L$2:$L$501,Homologacion!$C$2:$C$501,A8)) | D8: =IF(A8="","",SUMIFS(Homologacion!$M$2:$M$501,Homologacion!$C$2:$C$501,A8)) | E8: =IF(A8="","",C8-D8) | F8: =IF(A8="","",COUNTIFS(Homologacion!$C$2:$C$501,A8,Homologacion!$U$2:$U$501,"Pendiente")) | G8: =IF(A8="","",COUNTIFS(Homologacion!$C$2:$C$501,A8,Homologacion!$Q$2:$Q$501,"Pendiente"))
B9: =IF(A9="","",COUNTIFS(Homologacion!$C$2:$C$501,A9)) | C9: =IF(A9="","",SUMIFS(Homologacion!$L$2:$L$501,Homologacion!$C$2:$C$501,A9)) | D9: =IF(A9="","",SUMIFS(Homologacion!$M$2:$M$501,Homologacion!$C$2:$C$501,A9)) | E9: =IF(A9="","",C9-D9) | F9: =IF(A9="","",COUNTIFS(Homologacion!$C$2:$C$501,A9,Homologacion!$U$2:$U$501,"Pendiente")) | G9: =IF(A9="","",COUNTIFS(Homologacion!$C$2:$C$501,A9,Homologacion!$Q$2:$Q$501,"Pendiente"))
B10: =IF(A10="","",COUNTIFS(Homologacion!$C$2:$C$501,A10)) | C10: =IF(A10="","",SUMIFS(Homologacion!$L$2:$L$501,Homologacion!$C$2:$C$501,A10)) | D10: =IF(A10="","",SUMIFS(Homologacion!$M$2:$M$501,Homologacion!$C$2:$C$501,A10)) | E10: =IF(A10="","",C10-D10) | F10: =IF(A10="","",COUNTIFS(Homologacion!$C$2:$C$501,A10,Homologacion!$U$2:$U$501,"Pendiente")) | G10: =IF(A10="","",COUNTIFS(Homologacion!$C$2:$C$501,A10,Homologacion!$Q$2:$Q$501,"Pendiente"))
B11: =IF(A11="","",COUNTIFS(Homologacion!$C$2:$C$501,A11)) | C11: =IF(A11="","",SUMIFS(Homologacion!$L$2:$L$501,Homologacion!$C$2:$C$501,A11)) | D11: =IF(A11="","",SUMIFS(Homologacion!$M$2:$M$501,Homologacion!$C$2:$C$501,A11)) | E11: =IF(A11="","",C11-D11) | F11: =IF(A11="","",COUNTIFS(Homologacion!$C$2:$C$501,A11,Homologacion!$U$2:$U$501,"Pendiente")) | G11: =IF(A11="","",COUNTIFS(Homologacion!$C$2:$C$501,A11,Homologacion!$Q$2:$Q$501,"Pendiente"))
B12: =IF(A12="","",COUNTIFS(Homologacion!$C$2:$C$501,A12)) | C12: =IF(A12="","",SUMIFS(Homologacion!$L$2:$L$501,Homologacion!$C$2:$C$501,A12)) | D12: =IF(A12="","",SUMIFS(Homologacion!$M$2:$M$501,Homologacion!$C$2:$C$501,A12)) | E12: =IF(A12="","",C12-D12) | F12: =IF(A12="","",COUNTIFS(Homologacion!$C$2:$C$501,A12,Homologacion!$U$2:$U$501,"Pendiente")) | G12: =IF(A12="","",COUNTIFS(Homologacion!$C$2:$C$501,A12,Homologacion!$Q$2:$Q$501,"Pendiente"))
B13: =IF(A13="","",COUNTIFS(Homologacion!$C$2:$C$501,A13)) | C13: =IF(A13="","",SUMIFS(Homologacion!$L$2:$L$501,Homologacion!$C$2:$C$501,A13)) | D13: =IF(A13="","",SUMIFS(Homologacion!$M$2:$M$501,Homologacion!$C$2:$C$501,A13)) | E13: =IF(A13="","",C13-D13) | F13: =IF(A13="","",COUNTIFS(Homologacion!$C$2:$C$501,A13,Homologacion!$U$2:$U$501,"Pendiente")) | G13: =IF(A13="","",COUNTIFS(Homologacion!$C$2:$C$501,A13,Homologacion!$Q$2:$Q$501,"Pendiente"))
... B41: =IF(A41="","",COUNTIFS(Homologacion!$C$2:$C$501,A41)) | C41: =IF(A41="","",SUMIFS(Homologacion!$L$2:$L$501,Homologacion!$C$2:$C$501,A41)) | D41: =IF(A41="","",SUMIFS(Homologacion!$M$2:$M$501,Homologacion!$C$2:$C$501,A41)) | E41: =IF(A41="","",C41-D41) | F41: =IF(A41="","",COUNTIFS(Homologacion!$C$2:$C$501,A41,Homologacion!$U$2:$U$501,"Pendiente")) | G41: =IF(A41="","",COUNTIFS(Homologacion!$C$2:$C$501,A41,Homologacion!$Q$2:$Q$501,"Pendiente"))
