Workbook

Sheet CC_TABIQUERIA SIN SOLAQUEO
B3: COMPARATIVO - TABIQUERÍA A TODO COSTO SIN SOLAQUEO
B4: FECHA: 04 DE NOVIEMBRE DEL 2025
B6: PRESUPUESTO META | H6: MAQUIJAL INGENIEROS SAC
B7: Descripción | C7: Unid | D7: Metrado | E7: P.Unitario (S/) | F7: P.Parcial (S/) | H7: Cant. | I7: P.Unitario (S/) | J7: P.Parcial (S/)
B9: TABIQUERÍA | F9: =+F11+F15+F22 -> 365816.83 | J9: =+J11+J15+J22 -> 340789.27
B11: SOTANOS | F11: =SUM(F12:F13) -> 9558.8143 | J11: =SUM(J12:J13) -> 8117.9179
B12: Muro de ladrillo silico calcareo - Solaqueado P10 | C12: m2 | D12: 38.82 | E12: =117.38-'APU 5.2 SOLAQUEO'!H4 -> 106.51 | F12: =PRODUCT(D12:E12) -> 4134.7182 | H12: =+D12 -> 38.82 | I12: 93.12 | J12: =PRODUCT(H12:I12) -> 3614.9184 | L12: =I12-E12 -> -13.39
B13: Muro de ladrillo silico calcareo - Solaqueado P14 RF | C13: m2 | D13: 41.83 | E13: =140.54-'APU 5.2 SOLAQUEO'!H4 -> 129.67 | F13: =PRODUCT(D13:E13) -> 5424.0961 | H13: =+D13 -> 41.83 | I13: 107.65 | J13: =PRODUCT(H13:I13) -> 4502.9995 | L13: =I13-E13 -> -22.02
B15: SUPERESTRUCTURA (NO INCLUYE COSTO DE ACERO) | F15: =SUM(F16:F20) -> 356258.01 | J15: =SUM(J16:J20) -> 310856.55
B16: Muro de ladrillo silico calcareo - Solaqueado P10 | C16: m2 | D16: 2345.71 | E16: =117.38-0.82-'APU 5.2 SOLAQUEO'!H4 -> 105.69 | F16: =PRODUCT(D16:E16) -> 247918.09 | H16: =+D16 -> 2345.71 | I16: 93.12 | J16: =PRODUCT(H16:I16) -> 218432.52 | K16: =J16/J15 -> 0.70267947 | L16: =I16-E16 -> -12.57
B17: Muro de ladrillo silico calcareo - Solaqueado P10 RF | C17: m2 | D17: 343.51 | E17: =119.56-0.82-'APU 5.2 SOLAQUEO'!H4 -> 107.87 | F17: =PRODUCT(D17:E17) -> 37054.424 | H17: =+D17 -> 343.51 | I17: 95.28 | J17: =PRODUCT(H17:I17) -> 32729.633 | L17: =I17-E17 -> -12.59
B18: Muro de ladrillo silico calcareo - Solaqueado P14 | C18: m2 | D18: 60.71 | E18: =138.52-0.82-'APU 5.2 SOLAQUEO'!H4 -> 126.83 | F18: =PRODUCT(D18:E18) -> 7699.8493 | H18: =+D18 -> 60.71 | I18: 105 | J18: =PRODUCT(H18:I18) -> 6374.55 | L18: =I18-E18 -> -21.83
B19: Muro de ladrillo silico calcareo - Soalqueado P14 RF | C19: m2 | D19: 485.55 | E19: =140.54-0.82-'APU 5.2 SOLAQUEO'!H4 -> 128.85 | F19: =PRODUCT(D19:E19) -> 62563.118 | H19: =+D19 -> 485.55 | I19: 107.65 | J19: =PRODUCT(H19:I19) -> 52269.458 | K19: =J19/J15 -> 0.16814655 | L19: =I19-E19 -> -21.2
B20: Muro de ladrillo silico calcareo - Solaqueado P20 | C20: m2 | D20: 5.64 | E20: =192.99-0.82-'APU 5.2 SOLAQUEO'!H4 -> 181.3 | F20: =PRODUCT(D20:E20) -> 1022.532 | H20: =+D20 -> 5.64 | I20: 186.24 | J20: =PRODUCT(H20:I20) -> 1050.3936 | L20: =I20-E20 -> 4.94
B22: SELLADO DE MUROS CORTAFUEGO | J22: =SUM(J23) -> 21814.8
B23: Muro de ladrillo silico calcareo - Solaqueado P10 | C23: m2 | D23: 1558.2 | H23: =+D23 -> 1558.2 | I23: 14 | J23: =PRODUCT(H23:I23) -> 21814.8
E26: PARCIAL (SIN IGV) | F26: =+F9 -> 365816.83 | J26: =+J9 -> 340789.27
E27: GASTOS GENERALES + UTILIDAD | F27: 0 | I27: 0 | J27: =I27*J26 -> 0
E28: SUBTOTAL | F28: =+SUM(F26:F27) -> 365816.83 | J28: =J27+J26 -> 340789.27
E29: IGV (18%) | F29: =+F28*0.18 -> 65847.029 | J29: =J28*0.18 -> 61342.068
E30: TOTAL INC. IGV | F30: =F29+F28 -> 431663.86 | J30: =+J28+J29 -> 402131.34
B32: DELTA | H32: =+F30-J30 -> 29532.52
F33: ADELANTO / TIPO DE GARANTIA | H33: Val adelantada por s./ 25,000.00
F34: FRECUENCIA DE VALORIZACIONES | H34: Valorizacion semanal, Pago a 7 dias
F35: FONDO DE GARANTIA | H35: Retención del 5%
F36: CONTACTO
F38: CONSIDERACIONES: | H38: - No incluye personal de descarga ni acarreo vertical. - No incluye el acabado de pases de extractores, pases de manguera, pases ACI, tableros - Incluye acarreo horizontal con dos estocas. - Incluye eliminación de desmonte a zona de acopio o a través del chute. - No incluye el suministro ni armado de andamios. - Incluye el asentado de muros máximo hasta 3m de altura. - Los trabajos se realizaran según manual de instalacion por LA CASA. - Incluye acabados como solaqueo, derrames, bruñas y copado. - No incluye vigia para descarga de camiones. - Incluye el anclaje, asentado y acabados.
F40: N° DE OBRAS ACTUALES EN EJECUCION

Sheet CC_TABIQUERIA
B3: COMPARATIVO - TABIQUERÍA A TODO COSTO
B4: FECHA: 24 DE OCTUBRE DEL 2025
B6: PRESUPUESTO META | H6: MAQUIJAL INGENIEROS SAC | K6: DEIVID CONSTRUCCIONES EIRL | N6: VDCING | Q6: ROLEX CONSTRUCTORES SAC
B7: Descripción | C7: Unid | D7: Metrado | E7: P.Unitario (S/) | F7: P.Parcial (S/) | H7: Cant. | I7: P.Unitario (S/) | J7: P.Parcial (S/) | K7: Cant. | L7: P.Unitario (S/) | M7: P.Parcial (S/) | N7: Cant. | O7: P.Unitario (S/) | P7: P.Parcial (S/) | Q7: Cant. | R7: P.Unitario (S/) | S7: P.Parcial (S/)
B9: TABIQUERÍA | F9: =+F11+F15 -> 415049.85 | J9: =+J11+J15 -> 357173.84 | M9: =+M11+M15 -> 535802.79 | P9: =+P11+P15 -> 412055.64 | S9: =+S11+S15 -> 413345.14
B11: SOTANOS | F11: =SUM(F12:F13) -> 23339.864 | J11: =SUM(J12:J13) -> 19528.48 | M11: =SUM(M12:M13) -> 28834 | P11: =SUM(P12:P13) -> 22181.4 | S11: =SUM(S12:S13) -> 23625.593
B12: Muro de ladrillo silico calcareo - Solaqueado P10 | C12: m2 | D12: 83.3 | E12: 117.38 | F12: =PRODUCT(D12:E12) -> 9777.754 | H12: =+D12 -> 83.3 | I12: 102 | J12: =PRODUCT(H12:I12) -> 8496.6 | K12: =+D12 -> 83.3 | L12: 155 | M12: =PRODUCT(K12:L12) -> 12911.5 | N12: =+D12 -> 83.3 | O12: 118 | P12: =PRODUCT(N12:O12) -> 9829.4 | Q12: =+D12 -> 83.3 | R12: 113.06 | S12: =PRODUCT(Q12:R12) -> 9417.898
B13: Muro de ladrillo silico calcareo - Solaqueado P14 RF | C13: m2 | D13: 96.5 | E13: 140.54 | F13: =PRODUCT(D13:E13) -> 13562.11 | H13: =+D13 -> 96.5 | I13: 114.32 | J13: =PRODUCT(H13:I13) -> 11031.88 | K13: =+D13 -> 96.5 | L13: 165 | M13: =PRODUCT(K13:L13) -> 15922.5 | N13: =+D13 -> 96.5 | O13: 128 | P13: =PRODUCT(N13:O13) -> 12352 | Q13: =+D13 -> 96.5 | R13: 147.23 | S13: =PRODUCT(Q13:R13) -> 14207.695
B15: SUPERESTRUCTURA (NO INCLUYE COSTO DE ACERO) | F15: =SUM(F16:F20) -> 391709.98 | J15: =SUM(J16:J20) -> 337645.36 | M15: =SUM(M16:M20) -> 506968.79 | P15: =SUM(P16:P20) -> 389874.24 | S15: =SUM(S16:S20) -> 389719.54
B16: Muro de ladrillo silico calcareo - Solaqueado P10 | C16: m2 | D16: 2345.71 | E16: =117.38-0.82 -> 116.56 | F16: =PRODUCT(D16:E16) -> 273415.96 | H16: =+D16 -> 2345.71 | I16: 102 | J16: =PRODUCT(H16:I16) -> 239262.42 | K16: =+D16 -> 2345.71 | L16: 155 | M16: =PRODUCT(K16:L16) -> 363585.05 | N16: =+D16 -> 2345.71 | O16: 118 | P16: =PRODUCT(N16:O16) -> 276793.78 | Q16: =+D16 -> 2345.71 | R16: 113.06 | S16: =PRODUCT(Q16:R16) -> 265205.97
B17: Muro de ladrillo silico calcareo - Solaqueado P10 RF | C17: m2 | D17: 343.51 | E17: =119.56-0.82 -> 118.74 | F17: =PRODUCT(D17:E17) -> 40788.377 | H17: =+D17 -> 343.51 | I17: 105 | J17: =PRODUCT(H17:I17) -> 36068.55 | K17: =+D17 -> 343.51 | L17: 155 | M17: =PRODUCT(K17:L17) -> 53244.05 | N17: =+D17 -> 343.51 | O17: 122 | P17: =PRODUCT(N17:O17) -> 41908.22 | Q17: =+D17 -> 343.51 | R17: 127.12 | S17: =PRODUCT(Q17:R17) -> 43666.991
B18: Muro de ladrillo silico calcareo - Solaqueado P14 | C18: m2 | D18: 60.71 | E18: =138.52-0.82 -> 137.7 | F18: =PRODUCT(D18:E18) -> 8359.767 | H18: =+D18 -> 60.71 | I18: 112 | J18: =PRODUCT(H18:I18) -> 6799.52 | K18: =+D18 -> 60.71 | L18: 165 | M18: =PRODUCT(K18:L18) -> 10017.15 | N18: =+D18 -> 60.71 | O18: 124 | P18: =PRODUCT(N18:O18) -> 7528.04 | Q18: =+D18 -> 60.71 | R18: 128.87 | S18: =PRODUCT(Q18:R18) -> 7823.6977
B19: Muro de ladrillo silico calcareo - Soalqueado P14 RF | C19: m2 | D19: 485.55 | E19: =140.54-0.82 -> 139.72 | F19: =PRODUCT(D19:E19) -> 67841.046 | H19: =+D19 -> 485.55 | I19: 114.32 | J19: =PRODUCT(H19:I19) -> 55508.076 | K19: =+D19 -> 485.55 | L19: 165 | M19: =PRODUCT(K19:L19) -> 80115.75 | N19: =+D19 -> 485.55 | O19: 128 | P19: =PRODUCT(N19:O19) -> 62150.4 | Q19: =+D19 -> 485.55 | R19: 147.23 | S19: =PRODUCT(Q19:R19) -> 71487.526
B20: Muro de ladrillo silico calcareo - Solaqueado P20 | C20: m2 | D20: 6.79 | E20: =192.99-0.82 -> 192.17 | F20: =PRODUCT(D20:E20) -> 1304.8343 | H20: =+D20 -> 6.79 | J20: =PRODUCT(H20:I20) -> 6.79 | K20: =+D20 -> 6.79 | M20: =PRODUCT(K20:L20) -> 6.79 | N20: =+D20 -> 6.79 | O20: 220 | P20: =PRODUCT(N20:O20) -> 1493.8 | Q20: =+D20 -> 6.79 | R20: 226.12 | S20: =PRODUCT(Q20:R20) -> 1535.3548
E23: PARCIAL (SIN IGV) | F23: =+F9 -> 415049.85 | J23: =+J9 -> 357173.84 | M23: =+M9 -> 535802.79 | P23: =+P9 -> 412055.64 | S23: =+S9 -> 413345.14
E24: GASTOS GENERALES + UTILIDAD | F24: 0 | I24: 0 | J24: =I24*J23 -> 0 | L24: 0 | M24: =L24*M23 -> 0 | O24: =+P24/P23 -> 0.13857352 | P24: 57100 | R24: =+S24/S23 -> 0.05443393 | S24: 22500
E25: SUBTOTAL | F25: =+SUM(F23:F24) -> 415049.85 | J25: =J24+J23 -> 357173.84 | M25: =M24+M23 -> 535802.79 | P25: =P24+P23 -> 469155.64 | S25: =S24+S23 -> 435845.14
E26: IGV (18%) | F26: =+F25*0.18 -> 74708.972 | J26: =J25*0.18 -> 64291.29 | M26: =M25*0.18 -> 96444.502 | P26: =P25*0.18 -> 84448.015 | S26: =S25*0.18 -> 78452.124
E27: TOTAL INC. IGV | F27: =F26+F25 -> 489758.82 | J27: =+J25+J26 -> 421465.13 | M27: =+M25+M26 -> 632247.29 | P27: =+P25+P26 -> 553603.66 | S27: =+S25+S26 -> 514297.26
B29: DELTA | H29: =+F27-J27 -> 68293.692 | K29: =+F27-M27 -> -142488.47 | N29: =+F27-P27 -> -63844.837 | Q29: =+F27-S27 -> -24538.442
F30: ADELANTO / TIPO DE GARANTIA | H30: 30% de adelanto (126,439.54 soles) | K30: 40% de adelanto (160,740.84 soles) | N30: 5000 soles | Q30: 20% de adelanto
F31: FRECUENCIA DE VALORIZACIONES | H31: Valorizacion semanal, Pago a 7 dias | K31: Valorizacion semanal, Pago a 7 dias | N31: Valorizacion semanal, Pago a 7 dias | Q31: Valorizacion semanal, Pago a 7 dias
F32: FONDO DE GARANTIA | H32: Retención del 5% | K32: Retención del 5% | N32: Retención del 5% | Q32: Retención del 5%
F33: CONTACTO
F35: CONSIDERACIONES: | H35: - No incluye personal de descarga ni acarreo vertical. - No incluye el acabado de pases de extractores, pases de manguera, pases ACI, tableros - Incluye acarreo horizontal con dos estocas. - Incluye eliminación de desmonte a zona de acopio o a través del chute. - No incluye el suministro ni armado de andamios. - Incluye el asentado de muros máximo hasta 3m de altura. - Los trabajos se realizaran según manual de instalacion por LA CASA. - Incluye acabados como solaqueo, derrames, bruñas y copado. - No incluye vigia para descarga de camiones. - Incluye el anclaje, asentado y acabados. | K35: - La cotización está incluido a todo costo. Incluido transporte y herramientas. - Está considerado ladrillo, mortero, concreto, epóxico, tecnopor, ojos chinos, discos, brocas - El PTO considera EMOS, SCTR, EPP - El PTO no considera acarreo vertical. Considera solo acarreo horizontal | N35: - Fondo de garantía: Se descontará el 5% por cada valorización y será devuelto en el plazo máximo de 6 meses después de obtener el acta de entrega de obra suscrito por el responsable del proyecto. - El cliente deberá proporcionar lo siguiente: - Los Planos firmados en señal de su aprobación del responsable. - Suministro de áreas para oficina y vestuario del personal (contratista). - Suministro eléctrico y punto de agua en cada piso de trabajo. - Acero en todos los casos. - Las instalaciones eléctricas y sanitarias deberán estar colocadas previamente a la construcción del muro y fijadas previas al solaqueo del muro. Si estas no estuvieran colocadas y fijadas al terminar la instalación de los tabiques del piso correspondiente, los resanes serán por cuenta del cliente. - Si el muro estuviera mal construido por un error de trazo el costo de la reparación será por cuenta del cliente. Respetamos los trazos liberados. - Suministro de condiciones seguras para el trabajo (barandas, ductos, señalización y accesos). - Iluminación de áreas comunes y rutas de evacuación. - Suministro de implementos de protección colectiva. (Proporciona almacén). - Disponer de capacidad y área para la recepción de materiales según el cronograma de obra. | Q35: CONSIDERACIONES OPERATIVAS - El presupuesto es A TODO, bajo la modalidad de PRECIOS UNITARIOS - Incluye únicamente los trabajos relacionados a tabiquería, los muros serán llenados parcial y totalmente según indica en el detalle de la partida, y con acabado solaqueado. No incluye acabado exterior. - El cliente debe proporcionar punto de agua en cada piso, punto de energia, SSHH, comedor, y chute para evacuación de desmonte. - La intervención se dará posterior a la liberación de instalaciones sanitarias, instalaciones eléctricas y de gas si las hubieran. Idealmente, deben estar tarrajeadas y liberadas las vigas y columnas. NO INCLUYE * Acero, recepción y descarga de materiales, izaje vertical, andamios. * Trabajos de instalaciones sanitarias, eléctricas y topográficas. INCLUYE * BLOQUETAS, CONCRETO LIQUIDO, MORTERO, OJO CHINO, ADHESIVO EPÓXICO, TECNOPOR O SELLO CORTAFUEGO. * Recepción de material y acarreo y distribución horizontal. * Incluye caseta de almacén temporal armado de madera machimbrada o equivalente. * Personal técnico calificado para estos trabajos, responsable de obra, maestro y PDR si se requiere. * Manipuleo de los materiales dentro de nuestras instalaciones. * Las herramientas y equipos son normados por el reglamento de seguridad nacional. * Se entregaran Las areas limpias de nuestros trabajos * Calidad en nuestros servicios. * Se contara con todos los implementos de seguridad según norma técnica de seguridad para este tipo de trabajo.
F37: N° DE OBRAS ACTUALES EN EJECUCION

Sheet APU 5.2 SOLAQUEO
B2: APU SOLAQUEO MUROS DE CONCRETO EN INTERIORES
C4: 2.3.1.2.2 | D4: SOLAQUEO DE MUROS INTERIORES | E4: m2 | H4: =SUM(H8:H10,H14:H18) -> 10.87
C6: Mano de obra
C8: MOMOCP01 | D8: CAPATAZ | E8: hh | F8: 0.1 | G8: 34.77 | H8: 0.7 | I8: PEN
C9: MOMOOP01 | D9: OPERARIO | E9: hh | F9: 1 | G9: 28.73 | H9: 5.81 | I9: PEN
C10: MOMOAY01 | D10: AYUDANTE | E10: hh | F10: 0.333 | G10: 20.48 | H10: 1.38 | I10: PEN
C12: Materiales y herramientas
C14: %EQHMHER03 | D14: HERRAMIENTAS MANUALES 3% | E14: % | F14: 0.0789 | G14: 3 | H14: 0.24 | I14: PEN
C15: MAAGAR02 | D15: ARENA FINA | E15: m3 | F15: 0.004 | G15: 42.5 | H15: 0.17 | I15: PEN
C16: MACECE01 | D16: CEMENTO PORTLAND TI | E16: bls | F16: 0.065 | G16: 21 | H16: 1.37 | I16: PEN
C17: EQECAND01 | D17: ANDAMIO METALICO | E17: mes | F17: 0.0222 | G17: 200 | H17: 0.9 | I17: PEN
C18: EQECAMO01 | D18: AMOLADORA DE 4.5'' | E18: u | F18: 0.1236 | G18: 12 | H18: 0.3 | I18: PEN

Sheet CC_TABIQUERIA (MO)
B3: COMPARATIVO - SC MANO DE OBRA - TABIQUERIA
B4: FECHA: 24 DE OCTUBRE DEL 2025
B6: PRESUPUESTO META | H6: MAQUIJAL INGENIEROS SAC | K6: DEIVID CONSTRUCCIONES EIRL | N6: ROLEX CONSTRUCTORES SAC
B7: Descripción | C7: Unid | D7: Metrado | E7: P.Unitario (S/) | F7: P.Parcial (S/) | H7: Cant. | I7: P.Unitario (S/) | J7: P.Parcial (S/) | K7: Cant. | L7: P.Unitario (S/) | M7: P.Parcial (S/) | N7: Cant. | O7: P.Unitario (S/) | P7: P.Parcial (S/)
B9: TABIQUERÍA | F9: =+F11+F15 -> 415049.85 | J9: =+J11+J15+J21 -> #REF! | M9: =+M11+M15+M21 -> #REF! | P9: =+P11+P15+P21 -> #REF!
B11: SOTANOS | F11: =SUM(F12:F13) -> 23339.864 | J11: =SUM(J12:J13) -> 11909.95 | M11: =SUM(M12:M13) -> 10788 | P11: =SUM(P12:P13) -> 11809.9
B12: Muro de ladrillo silico calcareo - Solaqueado P10 | C12: m2 | D12: 83.3 | E12: 117.38 | F12: =PRODUCT(D12:E12) -> 9777.754 | H12: =+D12 -> 83.3 | I12: 62 | J12: =PRODUCT(H12:I12) -> 5164.6 | K12: =+D12 -> 83.3 | L12: 60 | M12: =PRODUCT(K12:L12) -> 4998 | N12: =+D12 -> 83.3 | O12: 63 | P12: =PRODUCT(N12:O12) -> 5247.9
B13: Muro de ladrillo silico calcareo - Solaqueado P14 RF | C13: m2 | D13: 96.5 | E13: 140.54 | F13: =PRODUCT(D13:E13) -> 13562.11 | H13: =+D13 -> 96.5 | I13: 69.9 | J13: =PRODUCT(H13:I13) -> 6745.35 | K13: =+D13 -> 96.5 | L13: 60 | M13: =PRODUCT(K13:L13) -> 5790 | N13: =+D13 -> 96.5 | O13: 68 | P13: =PRODUCT(N13:O13) -> 6562
B15: SUPERESTRUCTURA (NO INCLUYE COSTO DE ACERO) | F15: =SUM(F16:F20) -> 391709.98 | J15: =SUM(J16:J20) -> 204806.65 | M15: =SUM(M16:M20) -> 194536.2 | P15: =SUM(P16:P20) -> 208391.9
B16: Muro de ladrillo silico calcareo - Solaqueado P10 | C16: m2 | D16: 2345.71 | E16: =117.38-0.82 -> 116.56 | F16: =PRODUCT(D16:E16) -> 273415.96 | H16: =+D16 -> 2345.71 | I16: 62 | J16: =PRODUCT(H16:I16) -> 145434.02 | K16: =+D16 -> 2345.71 | L16: 60 | M16: =PRODUCT(K16:L16) -> 140742.6 | N16: =+D16 -> 2345.71 | O16: 63 | P16: =PRODUCT(N16:O16) -> 147779.73
B17: Muro de ladrillo silico calcareo - Solaqueado P10 RF | C17: m2 | D17: 343.51 | E17: =119.56-0.82 -> 118.74 | F17: =PRODUCT(D17:E17) -> 40788.377 | H17: =+D17 -> 343.51 | I17: 62 | J17: =PRODUCT(H17:I17) -> 21297.62 | K17: =+D17 -> 343.51 | L17: 60 | M17: =PRODUCT(K17:L17) -> 20610.6 | N17: =+D17 -> 343.51 | O17: 66 | P17: =PRODUCT(N17:O17) -> 22671.66
B18: Muro de ladrillo silico calcareo - Solaqueado P14 | C18: m2 | D18: 60.71 | E18: =138.52-0.82 -> 137.7 | F18: =PRODUCT(D18:E18) -> 8359.767 | H18: =+D18 -> 60.71 | I18: 68 | J18: =PRODUCT(H18:I18) -> 4128.28 | K18: =+D18 -> 60.71 | L18: 60 | M18: =PRODUCT(K18:L18) -> 3642.6 | N18: =+D18 -> 60.71 | O18: 67 | P18: =PRODUCT(N18:O18) -> 4067.57
B19: Muro de ladrillo silico calcareo - Soalqueado P14 RF | C19: m2 | D19: 485.55 | E19: =140.54-0.82 -> 139.72 | F19: =PRODUCT(D19:E19) -> 67841.046 | H19: =+D19 -> 485.55 | I19: 69.9 | J19: =PRODUCT(H19:I19) -> 33939.945 | K19: =+D19 -> 485.55 | L19: 60 | M19: =PRODUCT(K19:L19) -> 29133 | N19: =+D19 -> 485.55 | O19: 68 | P19: =PRODUCT(N19:O19) -> 33017.4
B20: Muro de ladrillo silico calcareo - Solaqueado P20 | C20: m2 | D20: 6.79 | E20: =192.99-0.82 -> 192.17 | F20: =PRODUCT(D20:E20) -> 1304.8343 | H20: =+D20 -> 6.79 | J20: =PRODUCT(H20:I20) -> 6.79 | K20: =+D20 -> 6.79 | L20: 60 | M20: =PRODUCT(K20:L20) -> 407.4 | N20: =+D20 -> 6.79 | O20: 126 | P20: =PRODUCT(N20:O20) -> 855.54
B21: MATERIAL Y CONSUMIBLES SEGÚN COT. "LA CASA" | J21: =SUM(J22:J28) -> #REF! | M21: =SUM(M22:M28) -> #REF! | P21: =SUM(P22:P28) -> #REF!
B22: Ladrillo Silico Calcareo P-10 (La CASA) incluye flete | C22: mll | H22: =+#REF! -> #REF! | I22: =25816/5.6 -> 4610 | J22: =PRODUCT(H22:I22) -> #REF! | K22: =+#REF! -> #REF! | L22: =25816/5.6 -> 4610 | M22: =PRODUCT(K22:L22) -> #REF! | N22: =+#REF! -> #REF! | O22: =25816/5.6 -> 4610 | P22: =PRODUCT(N22:O22) -> #REF!
B23: Ladrillo Silico Calcareo P-14 (La CASA) incluye flete | C23: mll | H23: =+#REF! -> #REF! | I23: =5750.64/1.008 -> 5705 | J23: =PRODUCT(H23:I23) -> #REF! | K23: =+#REF! -> #REF! | L23: =5750.64/1.008 -> 5705 | M23: =PRODUCT(K23:L23) -> #REF! | N23: =+#REF! -> #REF! | O23: =5750.64/1.008 -> 5705 | P23: =PRODUCT(N23:O23) -> #REF!
B24: Mortero grueso para muros divisorios (incluye flete) | C24: bls | H24: =+#REF! -> #REF! | I24: 8.6 | J24: =PRODUCT(H24:I24) -> #REF! | K24: =+#REF! -> #REF! | L24: 8.6 | M24: =PRODUCT(K24:L24) -> #REF! | N24: =+#REF! -> #REF! | O24: 8.6 | P24: =PRODUCT(N24:O24) -> #REF!
B25: Concreto para muros divisorios (incluye flete) | C25: bls | H25: =+#REF! -> #REF! | I25: 9.4 | J25: =PRODUCT(H25:I25) -> #REF! | K25: =+#REF! -> #REF! | L25: 9.4 | M25: =PRODUCT(K25:L25) -> #REF! | N25: =+#REF! -> #REF! | O25: 9.4 | P25: =PRODUCT(N25:O25) -> #REF!
B26: Mortero fino para solaqueo de muros (incluye flete) | C26: bls | H26: =+#REF! -> #REF! | I26: 8.6 | J26: =PRODUCT(H26:I26) -> #REF! | K26: =+#REF! -> #REF! | L26: 8.6 | M26: =PRODUCT(K26:L26) -> #REF! | N26: =+#REF! -> #REF! | O26: 8.6 | P26: =PRODUCT(N26:O26) -> #REF!
B27: Ojos chinos (para acero de 3/8") | C27: und | H27: 1600 | I27: 1.1 | J27: =PRODUCT(H27:I27) -> 1760 | K27: 1600 | L27: 1.1 | M27: =PRODUCT(K27:L27) -> 1760 | N27: 1600 | O27: 1.1 | P27: =PRODUCT(N27:O27) -> 1760
E30: PARCIAL (SIN IGV) | F30: =+F9 -> 415049.85 | J30: =+J9 -> #REF! | M30: =+M9 -> #REF! | P30: =+P9 -> #REF!
E31: GASTOS GENERALES + UTILIDAD | F31: 0 | I31: 0 | J31: =I31*J30 -> #REF! | L31: 0 | M31: =L31*M30 -> #REF! | P31: 22500
E32: SUBTOTAL | F32: =+SUM(F30:F31) -> 415049.85 | J32: =J31+J30 -> #REF! | M32: =M31+M30 -> #REF! | P32: =P31+P30 -> #REF!
E33: IGV (18%) | F33: =+F32*0.18 -> 74708.972 | J33: =J32*0.18 -> #REF! | M33: =M32*0.18 -> #REF! | P33: =P32*0.18 -> #REF!
E34: TOTAL INC. IGV | F34: =F33+F32 -> 489758.82 | J34: =+J32+J33 -> #REF! | M34: =+M32+M33 -> #REF! | P34: =+P32+P33 -> #REF!
B36: DELTA | H36: =+F34-J34 -> #REF! | K36: =+F34-M34 -> #REF! | N36: =+F34-P34 -> #REF!
F37: ADELANTO / TIPO DE GARANTIA | H37: No | K37: No | N37: No
F38: FRECUENCIA DE VALORIZACIONES | H38: Valorizacion semanal, Pago a 7 dias | K38: Valorizacion semanal, Pago a 7 dias | N38: Valorizacion semanal, Pago a 7 dias
F39: FONDO DE GARANTIA | H39: Retención del 5% | K39: Retención del 5% | N39: Retención del 5%
F40: CONTACTO
F42: CONSIDERACIONES: | H42: - No incluye personal de descarga ni acarreo vertical. - No incluye el acabado de pases de extractores, pases de manguera, pases ACI, tableros - Incluye acarreo horizontal con dos estocas. - Incluye eliminación de desmonte a zona de acopio o a través del chute. - No incluye el suministro ni armado de andamios. - Incluye el asentado de muros máximo hasta 3m de altura. - Los trabajos se realizaran según manual de instalacion por LA CASA. - Incluye acabados como solaqueo, derrames, bruñas y copado. - No incluye vigia para descarga de camiones. - Incluye el anclaje, asentado y acabados. | K42: - Anclado, asentado, copado, solaqueado con derrames de puertas, ventanas, gruñas | N42: CONSIDERACIONES OPERATIVAS - El presupuesto es A TODO, bajo la modalidad de PRECIOS UNITARIOS - Incluye únicamente los trabajos relacionados a tabiquería, los muros serán llenados parcial y totalmente según indica en el detalle de la partida, y con acabado solaqueado. No incluye acabado exterior. - El cliente debe proporcionar punto de agua en cada piso, punto de energia, SSHH, comedor, y chute para evacuación de desmonte. - La intervención se dará posterior a la liberación de instalaciones sanitarias, instalaciones eléctricas y de gas si las hubieran. Idealmente, deben estar tarrajeadas y liberadas las vigas y columnas. NO INCLUYE * Acero, recepción y descarga de materiales, izaje vertical, andamios. * Trabajos de instalaciones sanitarias, eléctricas y topográficas. INCLUYE * BLOQUETAS, CONCRETO LIQUIDO, MORTERO, OJO CHINO, ADHESIVO EPÓXICO, TECNOPOR O SELLO CORTAFUEGO. * Recepción de material y acarreo y distribución horizontal. * Incluye caseta de almacén temporal armado de madera machimbrada o equivalente. * Personal técnico calificado para estos trabajos, responsable de obra, maestro y PDR si se requiere. * Manipuleo de los materiales dentro de nuestras instalaciones. * Las herramientas y equipos son normados por el reglamento de seguridad nacional. * Se entregaran Las areas limpias de nuestros trabajos * Calidad en nuestros servicios. * Se contara con todos los implementos de seguridad según norma técnica de seguridad para este tipo de trabajo.
F44: N° DE OBRAS ACTUALES EN EJECUCION

Sheet MAQUIJAL
C81: COTI 2

Sheet DEYVID CONST EIRL

Sheet VDCING

Sheet ROLEX
